{"pack":"Character Pack Facial Hair","packId":"character_pack_facial_hair","style":"flat-cartoon","ui":false,"spriteCount":130,"categories":{"prop":130},"capabilities":{"player":true,"enemies":false,"tiles":false,"items":false,"projectiles":false,"vehicles":false,"ui":false,"background":false,"effects":false,"animations":[]},"animations":[],"sprites":[{"id":"character_pack_facial_hair/facialHair_black (1)","name":"facialHair_black (1)","category":"prop","ext":"png","rel":"2D assets/Character Pack Facial Hair/PNG/Facial hair/Black/facialHair_black (1).png","w":41,"h":11},{"id":"character_pack_facial_hair/facialHair_black (2)","name":"facialHair_black (2)","category":"prop","ext":"png","rel":"2D assets/Character Pack Facial Hair/PNG/Facial hair/Black/facialHair_black (2).png","w":22,"h":7},{"id":"character_pack_facial_hair/facialHair_black (3)","name":"facialHair_black (3)","category":"prop","ext":"png","rel":"2D assets/Character Pack Facial Hair/PNG/Facial hair/Black/facialHair_black (3).png","w":16,"h":23},{"id":"character_pack_facial_hair/facialHair_black (4)","name":"facialHair_black (4)","category":"prop","ext":"png","rel":"2D assets/Character Pack Facial Hair/PNG/Facial hair/Black/facialHair_black (4).png","w":48,"h":24},{"id":"character_pack_facial_hair/facialHair_black (5)","name":"facialHair_black (5)","category":"prop","ext":"png","rel":"2D assets/Character Pack Facial Hair/PNG/Facial hair/Black/facialHair_black (5).png","w":24,"h":42},{"id":"character_pack_facial_hair/facialHair_black (6)","name":"facialHair_black (6)","category":"prop","ext":"png","rel":"2D assets/Character Pack Facial Hair/PNG/Facial hair/Black/facialHair_black (6).png","w":48,"h":30},{"id":"character_pack_facial_hair/facialHair_black (7)","name":"facialHair_black (7)","category":"prop","ext":"png","rel":"2D assets/Character Pack Facial Hair/PNG/Facial hair/Black/facialHair_black (7).png","w":55,"h":57},{"id":"character_pack_facial_hair/facialHair_black (8)","name":"facialHair_black (8)","category":"prop","ext":"png","rel":"2D assets/Character Pack Facial Hair/PNG/Facial hair/Black/facialHair_black (8).png","w":33,"h":68},{"id":"character_pack_facial_hair/facialHair_black (9)","name":"facialHair_black (9)","category":"prop","ext":"png","rel":"2D assets/Character Pack Facial Hair/PNG/Facial hair/Black/facialHair_black (9).png","w":56,"h":58},{"id":"character_pack_facial_hair/facialHair_black (10)","name":"facialHair_black (10)","category":"prop","ext":"png","rel":"2D assets/Character Pack Facial Hair/PNG/Facial hair/Black/facialHair_black (10).png","w":45,"h":36},{"id":"character_pack_facial_hair/facialHair_black (11)","name":"facialHair_black (11)","category":"prop","ext":"png","rel":"2D assets/Character Pack Facial Hair/PNG/Facial hair/Black/facialHair_black (11).png","w":42,"h":18},{"id":"character_pack_facial_hair/facialHair_black (12)","name":"facialHair_black (12)","category":"prop","ext":"png","rel":"2D assets/Character Pack Facial Hair/PNG/Facial hair/Black/facialHair_black (12).png","w":42,"h":48},{"id":"character_pack_facial_hair/facialHair_black (13)","name":"facialHair_black (13)","category":"prop","ext":"png","rel":"2D assets/Character Pack Facial Hair/PNG/Facial hair/Black/facialHair_black (13).png","w":42,"h":30},{"id":"character_pack_facial_hair/facialHair_black (14)","name":"facialHair_black (14)","category":"prop","ext":"png","rel":"2D assets/Character Pack Facial Hair/PNG/Facial hair/Black/facialHair_black (14).png","w":30,"h":15},{"id":"character_pack_facial_hair/facialHair_black (15)","name":"facialHair_black (15)","category":"prop","ext":"png","rel":"2D assets/Character Pack Facial Hair/PNG/Facial hair/Black/facialHair_black (15).png","w":29,"h":8},{"id":"character_pack_facial_hair/facialHair_black (16)","name":"facialHair_black (16)","category":"prop","ext":"png","rel":"2D assets/Character Pack Facial Hair/PNG/Facial hair/Black/facialHair_black (16).png","w":6,"h":8},{"id":"character_pack_facial_hair/facialHair_blonde (1)","name":"facialHair_blonde (1)","category":"prop","ext":"png","rel":"2D assets/Character Pack Facial Hair/PNG/Facial hair/Blonde/facialHair_blonde (1).png","w":41,"h":12},{"id":"character_pack_facial_hair/facialHair_blonde (2)","name":"facialHair_blonde (2)","category":"prop","ext":"png","rel":"2D assets/Character Pack Facial Hair/PNG/Facial hair/Blonde/facialHair_blonde (2).png","w":22,"h":7},{"id":"character_pack_facial_hair/facialHair_blonde (3)","name":"facialHair_blonde (3)","category":"prop","ext":"png","rel":"2D assets/Character Pack Facial Hair/PNG/Facial hair/Blonde/facialHair_blonde (3).png","w":16,"h":23},{"id":"character_pack_facial_hair/facialHair_blonde (4)","name":"facialHair_blonde (4)","category":"prop","ext":"png","rel":"2D assets/Character Pack Facial Hair/PNG/Facial hair/Blonde/facialHair_blonde (4).png","w":48,"h":24},{"id":"character_pack_facial_hair/facialHair_blonde (5)","name":"facialHair_blonde (5)","category":"prop","ext":"png","rel":"2D assets/Character Pack Facial Hair/PNG/Facial hair/Blonde/facialHair_blonde (5).png","w":24,"h":42},{"id":"character_pack_facial_hair/facialHair_blonde (6)","name":"facialHair_blonde (6)","category":"prop","ext":"png","rel":"2D assets/Character Pack Facial Hair/PNG/Facial hair/Blonde/facialHair_blonde (6).png","w":48,"h":30},{"id":"character_pack_facial_hair/facialHair_blonde (7)","name":"facialHair_blonde (7)","category":"prop","ext":"png","rel":"2D assets/Character Pack Facial Hair/PNG/Facial hair/Blonde/facialHair_blonde (7).png","w":55,"h":57},{"id":"character_pack_facial_hair/facialHair_blonde (8)","name":"facialHair_blonde (8)","category":"prop","ext":"png","rel":"2D assets/Character Pack Facial Hair/PNG/Facial hair/Blonde/facialHair_blonde (8).png","w":33,"h":68},{"id":"character_pack_facial_hair/facialHair_blonde (9)","name":"facialHair_blonde (9)","category":"prop","ext":"png","rel":"2D assets/Character Pack Facial Hair/PNG/Facial hair/Blonde/facialHair_blonde (9).png","w":56,"h":58},{"id":"character_pack_facial_hair/facialHair_blonde (10)","name":"facialHair_blonde (10)","category":"prop","ext":"png","rel":"2D assets/Character Pack Facial Hair/PNG/Facial hair/Blonde/facialHair_blonde (10).png","w":45,"h":36},{"id":"character_pack_facial_hair/facialHair_blonde (11)","name":"facialHair_blonde (11)","category":"prop","ext":"png","rel":"2D assets/Character Pack Facial Hair/PNG/Facial hair/Blonde/facialHair_blonde (11).png","w":42,"h":18},{"id":"character_pack_facial_hair/facialHair_blonde (12)","name":"facialHair_blonde (12)","category":"prop","ext":"png","rel":"2D assets/Character Pack Facial Hair/PNG/Facial hair/Blonde/facialHair_blonde (12).png","w":42,"h":48},{"id":"character_pack_facial_hair/facialHair_blonde (13)","name":"facialHair_blonde (13)","category":"prop","ext":"png","rel":"2D assets/Character Pack Facial Hair/PNG/Facial hair/Blonde/facialHair_blonde (13).png","w":42,"h":30},{"id":"character_pack_facial_hair/facialHair_blonde (14)","name":"facialHair_blonde (14)","category":"prop","ext":"png","rel":"2D assets/Character Pack Facial Hair/PNG/Facial hair/Blonde/facialHair_blonde (14).png","w":30,"h":15},{"id":"character_pack_facial_hair/facialHair_blonde (15)","name":"facialHair_blonde (15)","category":"prop","ext":"png","rel":"2D assets/Character Pack Facial Hair/PNG/Facial hair/Blonde/facialHair_blonde (15).png","w":29,"h":8},{"id":"character_pack_facial_hair/facialHair_blonde (16)","name":"facialHair_blonde (16)","category":"prop","ext":"png","rel":"2D assets/Character Pack Facial Hair/PNG/Facial hair/Blonde/facialHair_blonde (16).png","w":6,"h":8},{"id":"character_pack_facial_hair/facialHair_brown (1)","name":"facialHair_brown (1)","category":"prop","ext":"png","rel":"2D assets/Character Pack Facial Hair/PNG/Facial hair/Brown 1/facialHair_brown (1).png","w":41,"h":12},{"id":"character_pack_facial_hair/facialHair_brown (2)","name":"facialHair_brown (2)","category":"prop","ext":"png","rel":"2D assets/Character Pack Facial Hair/PNG/Facial hair/Brown 1/facialHair_brown (2).png","w":22,"h":7},{"id":"character_pack_facial_hair/facialHair_brown (3)","name":"facialHair_brown (3)","category":"prop","ext":"png","rel":"2D assets/Character Pack Facial Hair/PNG/Facial hair/Brown 1/facialHair_brown (3).png","w":16,"h":23},{"id":"character_pack_facial_hair/facialHair_brown (4)","name":"facialHair_brown (4)","category":"prop","ext":"png","rel":"2D assets/Character Pack Facial Hair/PNG/Facial hair/Brown 1/facialHair_brown (4).png","w":48,"h":24},{"id":"character_pack_facial_hair/facialHair_brown (5)","name":"facialHair_brown (5)","category":"prop","ext":"png","rel":"2D assets/Character Pack Facial Hair/PNG/Facial hair/Brown 1/facialHair_brown (5).png","w":24,"h":42},{"id":"character_pack_facial_hair/facialHair_brown (6)","name":"facialHair_brown (6)","category":"prop","ext":"png","rel":"2D assets/Character Pack Facial Hair/PNG/Facial hair/Brown 1/facialHair_brown (6).png","w":48,"h":30},{"id":"character_pack_facial_hair/facialHair_brown (7)","name":"facialHair_brown (7)","category":"prop","ext":"png","rel":"2D assets/Character Pack Facial Hair/PNG/Facial hair/Brown 1/facialHair_brown (7).png","w":55,"h":57},{"id":"character_pack_facial_hair/facialHair_brown (8)","name":"facialHair_brown (8)","category":"prop","ext":"png","rel":"2D assets/Character Pack Facial Hair/PNG/Facial hair/Brown 1/facialHair_brown (8).png","w":33,"h":68},{"id":"character_pack_facial_hair/facialHair_brown (9)","name":"facialHair_brown (9)","category":"prop","ext":"png","rel":"2D assets/Character Pack Facial Hair/PNG/Facial hair/Brown 1/facialHair_brown (9).png","w":56,"h":58},{"id":"character_pack_facial_hair/facialHair_brown (10)","name":"facialHair_brown (10)","category":"prop","ext":"png","rel":"2D assets/Character Pack Facial Hair/PNG/Facial hair/Brown 1/facialHair_brown (10).png","w":45,"h":36},{"id":"character_pack_facial_hair/facialHair_brown (11)","name":"facialHair_brown (11)","category":"prop","ext":"png","rel":"2D assets/Character Pack Facial Hair/PNG/Facial hair/Brown 1/facialHair_brown (11).png","w":42,"h":18},{"id":"character_pack_facial_hair/facialHair_brown (12)","name":"facialHair_brown (12)","category":"prop","ext":"png","rel":"2D assets/Character Pack Facial Hair/PNG/Facial hair/Brown 1/facialHair_brown (12).png","w":42,"h":48},{"id":"character_pack_facial_hair/facialHair_brown (13)","name":"facialHair_brown (13)","category":"prop","ext":"png","rel":"2D assets/Character Pack Facial Hair/PNG/Facial hair/Brown 1/facialHair_brown (13).png","w":42,"h":30},{"id":"character_pack_facial_hair/facialHair_brown (14)","name":"facialHair_brown (14)","category":"prop","ext":"png","rel":"2D assets/Character Pack Facial Hair/PNG/Facial hair/Brown 1/facialHair_brown (14).png","w":30,"h":15},{"id":"character_pack_facial_hair/facialHair_brown (15)","name":"facialHair_brown (15)","category":"prop","ext":"png","rel":"2D assets/Character Pack Facial Hair/PNG/Facial hair/Brown 1/facialHair_brown (15).png","w":29,"h":8},{"id":"character_pack_facial_hair/facialHair_brown (16)","name":"facialHair_brown (16)","category":"prop","ext":"png","rel":"2D assets/Character Pack Facial Hair/PNG/Facial hair/Brown 1/facialHair_brown (16).png","w":6,"h":8},{"id":"character_pack_facial_hair/facialHair_brownAlt (1)","name":"facialHair_brownAlt (1)","category":"prop","ext":"png","rel":"2D assets/Character Pack Facial Hair/PNG/Facial hair/Brown 2/facialHair_brownAlt (1).png","w":41,"h":12},{"id":"character_pack_facial_hair/facialHair_brownAlt (2)","name":"facialHair_brownAlt (2)","category":"prop","ext":"png","rel":"2D assets/Character Pack Facial Hair/PNG/Facial hair/Brown 2/facialHair_brownAlt (2).png","w":22,"h":7},{"id":"character_pack_facial_hair/facialHair_brownAlt (3)","name":"facialHair_brownAlt (3)","category":"prop","ext":"png","rel":"2D assets/Character Pack Facial Hair/PNG/Facial hair/Brown 2/facialHair_brownAlt (3).png","w":16,"h":23},{"id":"character_pack_facial_hair/facialHair_brownAlt (4)","name":"facialHair_brownAlt (4)","category":"prop","ext":"png","rel":"2D assets/Character Pack Facial Hair/PNG/Facial hair/Brown 2/facialHair_brownAlt (4).png","w":48,"h":24},{"id":"character_pack_facial_hair/facialHair_brownAlt (5)","name":"facialHair_brownAlt (5)","category":"prop","ext":"png","rel":"2D assets/Character Pack Facial Hair/PNG/Facial hair/Brown 2/facialHair_brownAlt (5).png","w":24,"h":42},{"id":"character_pack_facial_hair/facialHair_brownAlt (6)","name":"facialHair_brownAlt (6)","category":"prop","ext":"png","rel":"2D assets/Character Pack Facial Hair/PNG/Facial hair/Brown 2/facialHair_brownAlt (6).png","w":48,"h":30},{"id":"character_pack_facial_hair/facialHair_brownAlt (7)","name":"facialHair_brownAlt (7)","category":"prop","ext":"png","rel":"2D assets/Character Pack Facial Hair/PNG/Facial hair/Brown 2/facialHair_brownAlt (7).png","w":55,"h":57},{"id":"character_pack_facial_hair/facialHair_brownAlt (8)","name":"facialHair_brownAlt (8)","category":"prop","ext":"png","rel":"2D assets/Character Pack Facial Hair/PNG/Facial hair/Brown 2/facialHair_brownAlt (8).png","w":33,"h":68},{"id":"character_pack_facial_hair/facialHair_brownAlt (9)","name":"facialHair_brownAlt (9)","category":"prop","ext":"png","rel":"2D assets/Character Pack Facial Hair/PNG/Facial hair/Brown 2/facialHair_brownAlt (9).png","w":56,"h":58},{"id":"character_pack_facial_hair/facialHair_brownAlt (10)","name":"facialHair_brownAlt (10)","category":"prop","ext":"png","rel":"2D assets/Character Pack Facial Hair/PNG/Facial hair/Brown 2/facialHair_brownAlt (10).png","w":45,"h":36},{"id":"character_pack_facial_hair/facialHair_brownAlt (11)","name":"facialHair_brownAlt (11)","category":"prop","ext":"png","rel":"2D assets/Character Pack Facial Hair/PNG/Facial hair/Brown 2/facialHair_brownAlt (11).png","w":42,"h":18},{"id":"character_pack_facial_hair/facialHair_brownAlt (12)","name":"facialHair_brownAlt (12)","category":"prop","ext":"png","rel":"2D assets/Character Pack Facial Hair/PNG/Facial hair/Brown 2/facialHair_brownAlt (12).png","w":42,"h":48},{"id":"character_pack_facial_hair/facialHair_brownAlt (13)","name":"facialHair_brownAlt (13)","category":"prop","ext":"png","rel":"2D assets/Character Pack Facial Hair/PNG/Facial hair/Brown 2/facialHair_brownAlt (13).png","w":42,"h":30},{"id":"character_pack_facial_hair/facialHair_brownAlt (14)","name":"facialHair_brownAlt (14)","category":"prop","ext":"png","rel":"2D assets/Character Pack Facial Hair/PNG/Facial hair/Brown 2/facialHair_brownAlt (14).png","w":30,"h":15},{"id":"character_pack_facial_hair/facialHair_brownAlt (15)","name":"facialHair_brownAlt (15)","category":"prop","ext":"png","rel":"2D assets/Character Pack Facial Hair/PNG/Facial hair/Brown 2/facialHair_brownAlt (15).png","w":29,"h":8},{"id":"character_pack_facial_hair/facialHair_brownAlt (16)","name":"facialHair_brownAlt (16)","category":"prop","ext":"png","rel":"2D assets/Character Pack Facial Hair/PNG/Facial hair/Brown 2/facialHair_brownAlt (16).png","w":6,"h":8},{"id":"character_pack_facial_hair/facialHair_grey (1)","name":"facialHair_grey (1)","category":"prop","ext":"png","rel":"2D assets/Character Pack Facial Hair/PNG/Facial hair/Grey/facialHair_grey (1).png","w":24,"h":42},{"id":"character_pack_facial_hair/facialHair_grey (2)","name":"facialHair_grey (2)","category":"prop","ext":"png","rel":"2D assets/Character Pack Facial Hair/PNG/Facial hair/Grey/facialHair_grey (2).png","w":48,"h":30},{"id":"character_pack_facial_hair/facialHair_grey (3)","name":"facialHair_grey (3)","category":"prop","ext":"png","rel":"2D assets/Character Pack Facial Hair/PNG/Facial hair/Grey/facialHair_grey (3).png","w":55,"h":57},{"id":"character_pack_facial_hair/facialHair_grey (4)","name":"facialHair_grey (4)","category":"prop","ext":"png","rel":"2D assets/Character Pack Facial Hair/PNG/Facial hair/Grey/facialHair_grey (4).png","w":33,"h":68},{"id":"character_pack_facial_hair/facialHair_grey (5)","name":"facialHair_grey (5)","category":"prop","ext":"png","rel":"2D assets/Character Pack Facial Hair/PNG/Facial hair/Grey/facialHair_grey (5).png","w":56,"h":58},{"id":"character_pack_facial_hair/facialHair_grey (6)","name":"facialHair_grey (6)","category":"prop","ext":"png","rel":"2D assets/Character Pack Facial Hair/PNG/Facial hair/Grey/facialHair_grey (6).png","w":45,"h":36},{"id":"character_pack_facial_hair/facialHair_grey (7)","name":"facialHair_grey (7)","category":"prop","ext":"png","rel":"2D assets/Character Pack Facial Hair/PNG/Facial hair/Grey/facialHair_grey (7).png","w":42,"h":18},{"id":"character_pack_facial_hair/facialHair_grey (8)","name":"facialHair_grey (8)","category":"prop","ext":"png","rel":"2D assets/Character Pack Facial Hair/PNG/Facial hair/Grey/facialHair_grey (8).png","w":42,"h":48},{"id":"character_pack_facial_hair/facialHair_grey (9)","name":"facialHair_grey (9)","category":"prop","ext":"png","rel":"2D assets/Character Pack Facial Hair/PNG/Facial hair/Grey/facialHair_grey (9).png","w":42,"h":30},{"id":"character_pack_facial_hair/facialHair_grey (10)","name":"facialHair_grey (10)","category":"prop","ext":"png","rel":"2D assets/Character Pack Facial Hair/PNG/Facial hair/Grey/facialHair_grey (10).png","w":30,"h":15},{"id":"character_pack_facial_hair/facialHair_grey (11)","name":"facialHair_grey (11)","category":"prop","ext":"png","rel":"2D assets/Character Pack Facial Hair/PNG/Facial hair/Grey/facialHair_grey (11).png","w":29,"h":8},{"id":"character_pack_facial_hair/facialHair_grey (12)","name":"facialHair_grey (12)","category":"prop","ext":"png","rel":"2D assets/Character Pack Facial Hair/PNG/Facial hair/Grey/facialHair_grey (12).png","w":6,"h":8},{"id":"character_pack_facial_hair/facialHair_grey (13)","name":"facialHair_grey (13)","category":"prop","ext":"png","rel":"2D assets/Character Pack Facial Hair/PNG/Facial hair/Grey/facialHair_grey (13).png","w":41,"h":12},{"id":"character_pack_facial_hair/facialHair_grey (14)","name":"facialHair_grey (14)","category":"prop","ext":"png","rel":"2D assets/Character Pack Facial Hair/PNG/Facial hair/Grey/facialHair_grey (14).png","w":22,"h":7},{"id":"character_pack_facial_hair/facialHair_grey (15)","name":"facialHair_grey (15)","category":"prop","ext":"png","rel":"2D assets/Character Pack Facial Hair/PNG/Facial hair/Grey/facialHair_grey (15).png","w":16,"h":23},{"id":"character_pack_facial_hair/facialHair_grey (16)","name":"facialHair_grey (16)","category":"prop","ext":"png","rel":"2D assets/Character Pack Facial Hair/PNG/Facial hair/Grey/facialHair_grey (16).png","w":48,"h":24},{"id":"character_pack_facial_hair/facialHair_red (1)","name":"facialHair_red (1)","category":"prop","ext":"png","rel":"2D assets/Character Pack Facial Hair/PNG/Facial hair/Red/facialHair_red (1).png","w":41,"h":12},{"id":"character_pack_facial_hair/facialHair_red (2)","name":"facialHair_red (2)","category":"prop","ext":"png","rel":"2D assets/Character Pack Facial Hair/PNG/Facial hair/Red/facialHair_red (2).png","w":22,"h":7},{"id":"character_pack_facial_hair/facialHair_red (3)","name":"facialHair_red (3)","category":"prop","ext":"png","rel":"2D assets/Character Pack Facial Hair/PNG/Facial hair/Red/facialHair_red (3).png","w":16,"h":23},{"id":"character_pack_facial_hair/facialHair_red (4)","name":"facialHair_red (4)","category":"prop","ext":"png","rel":"2D assets/Character Pack Facial Hair/PNG/Facial hair/Red/facialHair_red (4).png","w":48,"h":24},{"id":"character_pack_facial_hair/facialHair_red (5)","name":"facialHair_red (5)","category":"prop","ext":"png","rel":"2D assets/Character Pack Facial Hair/PNG/Facial hair/Red/facialHair_red (5).png","w":24,"h":42},{"id":"character_pack_facial_hair/facialHair_red (6)","name":"facialHair_red (6)","category":"prop","ext":"png","rel":"2D assets/Character Pack Facial Hair/PNG/Facial hair/Red/facialHair_red (6).png","w":48,"h":30},{"id":"character_pack_facial_hair/facialHair_red (7)","name":"facialHair_red (7)","category":"prop","ext":"png","rel":"2D assets/Character Pack Facial Hair/PNG/Facial hair/Red/facialHair_red (7).png","w":55,"h":57},{"id":"character_pack_facial_hair/facialHair_red (8)","name":"facialHair_red (8)","category":"prop","ext":"png","rel":"2D assets/Character Pack Facial Hair/PNG/Facial hair/Red/facialHair_red (8).png","w":33,"h":68},{"id":"character_pack_facial_hair/facialHair_red (9)","name":"facialHair_red (9)","category":"prop","ext":"png","rel":"2D assets/Character Pack Facial Hair/PNG/Facial hair/Red/facialHair_red (9).png","w":56,"h":58},{"id":"character_pack_facial_hair/facialHair_red (10)","name":"facialHair_red (10)","category":"prop","ext":"png","rel":"2D assets/Character Pack Facial Hair/PNG/Facial hair/Red/facialHair_red (10).png","w":45,"h":36},{"id":"character_pack_facial_hair/facialHair_red (11)","name":"facialHair_red (11)","category":"prop","ext":"png","rel":"2D assets/Character Pack Facial Hair/PNG/Facial hair/Red/facialHair_red (11).png","w":42,"h":18},{"id":"character_pack_facial_hair/facialHair_red (12)","name":"facialHair_red (12)","category":"prop","ext":"png","rel":"2D assets/Character Pack Facial Hair/PNG/Facial hair/Red/facialHair_red (12).png","w":42,"h":48},{"id":"character_pack_facial_hair/facialHair_red (13)","name":"facialHair_red (13)","category":"prop","ext":"png","rel":"2D assets/Character Pack Facial Hair/PNG/Facial hair/Red/facialHair_red (13).png","w":42,"h":30},{"id":"character_pack_facial_hair/facialHair_red (14)","name":"facialHair_red (14)","category":"prop","ext":"png","rel":"2D assets/Character Pack Facial Hair/PNG/Facial hair/Red/facialHair_red (14).png","w":30,"h":15},{"id":"character_pack_facial_hair/facialHair_red (15)","name":"facialHair_red (15)","category":"prop","ext":"png","rel":"2D assets/Character Pack Facial Hair/PNG/Facial hair/Red/facialHair_red (15).png","w":29,"h":8},{"id":"character_pack_facial_hair/facialHair_red (16)","name":"facialHair_red (16)","category":"prop","ext":"png","rel":"2D assets/Character Pack Facial Hair/PNG/Facial hair/Red/facialHair_red (16).png","w":6,"h":8},{"id":"character_pack_facial_hair/facialHair_tan (1)","name":"facialHair_tan (1)","category":"prop","ext":"png","rel":"2D assets/Character Pack Facial Hair/PNG/Facial hair/Tan/facialHair_tan (1).png","w":41,"h":12},{"id":"character_pack_facial_hair/facialHair_tan (2)","name":"facialHair_tan (2)","category":"prop","ext":"png","rel":"2D assets/Character Pack Facial Hair/PNG/Facial hair/Tan/facialHair_tan (2).png","w":22,"h":7},{"id":"character_pack_facial_hair/facialHair_tan (3)","name":"facialHair_tan (3)","category":"prop","ext":"png","rel":"2D assets/Character Pack Facial Hair/PNG/Facial hair/Tan/facialHair_tan (3).png","w":16,"h":23},{"id":"character_pack_facial_hair/facialHair_tan (4)","name":"facialHair_tan (4)","category":"prop","ext":"png","rel":"2D assets/Character Pack Facial Hair/PNG/Facial hair/Tan/facialHair_tan (4).png","w":48,"h":24},{"id":"character_pack_facial_hair/facialHair_tan (5)","name":"facialHair_tan (5)","category":"prop","ext":"png","rel":"2D assets/Character Pack Facial Hair/PNG/Facial hair/Tan/facialHair_tan (5).png","w":24,"h":42},{"id":"character_pack_facial_hair/facialHair_tan (6)","name":"facialHair_tan (6)","category":"prop","ext":"png","rel":"2D assets/Character Pack Facial Hair/PNG/Facial hair/Tan/facialHair_tan (6).png","w":48,"h":30},{"id":"character_pack_facial_hair/facialHair_tan (7)","name":"facialHair_tan (7)","category":"prop","ext":"png","rel":"2D assets/Character Pack Facial Hair/PNG/Facial hair/Tan/facialHair_tan (7).png","w":55,"h":57},{"id":"character_pack_facial_hair/facialHair_tan (8)","name":"facialHair_tan (8)","category":"prop","ext":"png","rel":"2D assets/Character Pack Facial Hair/PNG/Facial hair/Tan/facialHair_tan (8).png","w":33,"h":68},{"id":"character_pack_facial_hair/facialHair_tan (9)","name":"facialHair_tan (9)","category":"prop","ext":"png","rel":"2D assets/Character Pack Facial Hair/PNG/Facial hair/Tan/facialHair_tan (9).png","w":56,"h":58},{"id":"character_pack_facial_hair/facialHair_tan (10)","name":"facialHair_tan (10)","category":"prop","ext":"png","rel":"2D assets/Character Pack Facial Hair/PNG/Facial hair/Tan/facialHair_tan (10).png","w":45,"h":36},{"id":"character_pack_facial_hair/facialHair_tan (11)","name":"facialHair_tan (11)","category":"prop","ext":"png","rel":"2D assets/Character Pack Facial Hair/PNG/Facial hair/Tan/facialHair_tan (11).png","w":42,"h":18},{"id":"character_pack_facial_hair/facialHair_tan (12)","name":"facialHair_tan (12)","category":"prop","ext":"png","rel":"2D assets/Character Pack Facial Hair/PNG/Facial hair/Tan/facialHair_tan (12).png","w":42,"h":48},{"id":"character_pack_facial_hair/facialHair_tan (13)","name":"facialHair_tan (13)","category":"prop","ext":"png","rel":"2D assets/Character Pack Facial Hair/PNG/Facial hair/Tan/facialHair_tan (13).png","w":42,"h":30},{"id":"character_pack_facial_hair/facialHair_tan (14)","name":"facialHair_tan (14)","category":"prop","ext":"png","rel":"2D assets/Character Pack Facial Hair/PNG/Facial hair/Tan/facialHair_tan (14).png","w":30,"h":15},{"id":"character_pack_facial_hair/facialHair_tan (15)","name":"facialHair_tan (15)","category":"prop","ext":"png","rel":"2D assets/Character Pack Facial Hair/PNG/Facial hair/Tan/facialHair_tan (15).png","w":29,"h":8},{"id":"character_pack_facial_hair/facialHair_tan (16)","name":"facialHair_tan (16)","category":"prop","ext":"png","rel":"2D assets/Character Pack Facial Hair/PNG/Facial hair/Tan/facialHair_tan (16).png","w":6,"h":8},{"id":"character_pack_facial_hair/facialHair_white (1)","name":"facialHair_white (1)","category":"prop","ext":"png","rel":"2D assets/Character Pack Facial Hair/PNG/Facial hair/White/facialHair_white (1).png","w":41,"h":12},{"id":"character_pack_facial_hair/facialHair_white (2)","name":"facialHair_white (2)","category":"prop","ext":"png","rel":"2D assets/Character Pack Facial Hair/PNG/Facial hair/White/facialHair_white (2).png","w":22,"h":7},{"id":"character_pack_facial_hair/facialHair_white (3)","name":"facialHair_white (3)","category":"prop","ext":"png","rel":"2D assets/Character Pack Facial Hair/PNG/Facial hair/White/facialHair_white (3).png","w":16,"h":23},{"id":"character_pack_facial_hair/facialHair_white (4)","name":"facialHair_white (4)","category":"prop","ext":"png","rel":"2D assets/Character Pack Facial Hair/PNG/Facial hair/White/facialHair_white (4).png","w":48,"h":24},{"id":"character_pack_facial_hair/facialHair_white (5)","name":"facialHair_white (5)","category":"prop","ext":"png","rel":"2D assets/Character Pack Facial Hair/PNG/Facial hair/White/facialHair_white (5).png","w":24,"h":42},{"id":"character_pack_facial_hair/facialHair_white (6)","name":"facialHair_white (6)","category":"prop","ext":"png","rel":"2D assets/Character Pack Facial Hair/PNG/Facial hair/White/facialHair_white (6).png","w":48,"h":30},{"id":"character_pack_facial_hair/facialHair_white (7)","name":"facialHair_white (7)","category":"prop","ext":"png","rel":"2D assets/Character Pack Facial Hair/PNG/Facial hair/White/facialHair_white (7).png","w":55,"h":57},{"id":"character_pack_facial_hair/facialHair_white (8)","name":"facialHair_white (8)","category":"prop","ext":"png","rel":"2D assets/Character Pack Facial Hair/PNG/Facial hair/White/facialHair_white (8).png","w":33,"h":68},{"id":"character_pack_facial_hair/facialHair_white (9)","name":"facialHair_white (9)","category":"prop","ext":"png","rel":"2D assets/Character Pack Facial Hair/PNG/Facial hair/White/facialHair_white (9).png","w":56,"h":58},{"id":"character_pack_facial_hair/facialHair_white (10)","name":"facialHair_white (10)","category":"prop","ext":"png","rel":"2D assets/Character Pack Facial Hair/PNG/Facial hair/White/facialHair_white (10).png","w":45,"h":36},{"id":"character_pack_facial_hair/facialHair_white (11)","name":"facialHair_white (11)","category":"prop","ext":"png","rel":"2D assets/Character Pack Facial Hair/PNG/Facial hair/White/facialHair_white (11).png","w":42,"h":18},{"id":"character_pack_facial_hair/facialHair_white (12)","name":"facialHair_white (12)","category":"prop","ext":"png","rel":"2D assets/Character Pack Facial Hair/PNG/Facial hair/White/facialHair_white (12).png","w":42,"h":48},{"id":"character_pack_facial_hair/facialHair_white (13)","name":"facialHair_white (13)","category":"prop","ext":"png","rel":"2D assets/Character Pack Facial Hair/PNG/Facial hair/White/facialHair_white (13).png","w":42,"h":30},{"id":"character_pack_facial_hair/facialHair_white (14)","name":"facialHair_white (14)","category":"prop","ext":"png","rel":"2D assets/Character Pack Facial Hair/PNG/Facial hair/White/facialHair_white (14).png","w":30,"h":15},{"id":"character_pack_facial_hair/facialHair_white (15)","name":"facialHair_white (15)","category":"prop","ext":"png","rel":"2D assets/Character Pack Facial Hair/PNG/Facial hair/White/facialHair_white (15).png","w":29,"h":8},{"id":"character_pack_facial_hair/facialHair_white (16)","name":"facialHair_white (16)","category":"prop","ext":"png","rel":"2D assets/Character Pack Facial Hair/PNG/Facial hair/White/facialHair_white (16).png","w":6,"h":8},{"id":"character_pack_facial_hair/sheet_facialHair","name":"sheet_facialHair","category":"prop","ext":"png","rel":"2D assets/Character Pack Facial Hair/Spritesheet/sheet_facialHair.png","w":512,"h":512},{"id":"character_pack_facial_hair/vector_facialHair","name":"vector_facialHair","category":"prop","ext":"svg","rel":"2D assets/Character Pack Facial Hair/Vector/vector_facialHair.svg"}]}