{"pack":"Voxel Pack","packId":"voxel_pack","style":"flat-cartoon","ui":false,"spriteCount":193,"categories":{"character":26,"item":24,"projectile":2,"prop":78,"vehicle":1,"tile":40,"background":5,"ui":1,"enemy":8,"effect":8},"capabilities":{"player":true,"enemies":true,"tiles":true,"items":true,"projectiles":true,"vehicles":true,"ui":true,"background":true,"effects":true,"animations":[]},"animations":[],"sprites":[{"id":"voxel_pack/alien_arm","name":"alien_arm","category":"character","ext":"png","rel":"2D assets/Voxel Pack/PNG/Characters/Alien/alien_arm.png","w":16,"h":42},{"id":"voxel_pack/alien_body","name":"alien_body","category":"character","ext":"png","rel":"2D assets/Voxel Pack/PNG/Characters/Alien/alien_body.png","w":44,"h":47},{"id":"voxel_pack/alien_head","name":"alien_head","category":"character","ext":"png","rel":"2D assets/Voxel Pack/PNG/Characters/Alien/alien_head.png","w":92,"h":92},{"id":"voxel_pack/alien_leg","name":"alien_leg","category":"character","ext":"png","rel":"2D assets/Voxel Pack/PNG/Characters/Alien/alien_leg.png","w":28,"h":36},{"id":"voxel_pack/apple","name":"apple","category":"item","ext":"png","rel":"2D assets/Voxel Pack/PNG/Items/apple.png","w":128,"h":128},{"id":"voxel_pack/arrow","name":"arrow","category":"projectile","ext":"png","rel":"2D assets/Voxel Pack/PNG/Items/arrow.png","w":128,"h":128},{"id":"voxel_pack/axe_bronze","name":"axe_bronze","category":"prop","ext":"png","rel":"2D assets/Voxel Pack/PNG/Items/axe_bronze.png","w":128,"h":128},{"id":"voxel_pack/axe_diamond","name":"axe_diamond","category":"item","ext":"png","rel":"2D assets/Voxel Pack/PNG/Items/axe_diamond.png","w":128,"h":128},{"id":"voxel_pack/axe_gold","name":"axe_gold","category":"item","ext":"png","rel":"2D assets/Voxel Pack/PNG/Items/axe_gold.png","w":128,"h":128},{"id":"voxel_pack/axe_iron","name":"axe_iron","category":"prop","ext":"png","rel":"2D assets/Voxel Pack/PNG/Items/axe_iron.png","w":128,"h":128},{"id":"voxel_pack/axe_silver","name":"axe_silver","category":"prop","ext":"png","rel":"2D assets/Voxel Pack/PNG/Items/axe_silver.png","w":128,"h":128},{"id":"voxel_pack/boar_body","name":"boar_body","category":"character","ext":"png","rel":"2D assets/Voxel Pack/PNG/Characters/Boar/boar_body.png","w":86,"h":76},{"id":"voxel_pack/boar_head","name":"boar_head","category":"character","ext":"png","rel":"2D assets/Voxel Pack/PNG/Characters/Boar/boar_head.png","w":60,"h":79},{"id":"voxel_pack/boar_leg","name":"boar_leg","category":"character","ext":"png","rel":"2D assets/Voxel Pack/PNG/Characters/Boar/boar_leg.png","w":24,"h":23},{"id":"voxel_pack/boar_tail","name":"boar_tail","category":"character","ext":"png","rel":"2D assets/Voxel Pack/PNG/Characters/Boar/boar_tail.png","w":14,"h":31},{"id":"voxel_pack/boat","name":"boat","category":"vehicle","ext":"png","rel":"2D assets/Voxel Pack/PNG/Items/boat.png","w":128,"h":128},{"id":"voxel_pack/bow","name":"bow","category":"prop","ext":"png","rel":"2D assets/Voxel Pack/PNG/Items/bow.png","w":128,"h":128},{"id":"voxel_pack/bowArrow","name":"bowArrow","category":"projectile","ext":"png","rel":"2D assets/Voxel Pack/PNG/Items/bowArrow.png","w":128,"h":128},{"id":"voxel_pack/bowl","name":"bowl","category":"prop","ext":"png","rel":"2D assets/Voxel Pack/PNG/Items/bowl.png","w":128,"h":128},{"id":"voxel_pack/brick_grey","name":"brick_grey","category":"tile","ext":"png","rel":"2D assets/Voxel Pack/PNG/Tiles/brick_grey.png","w":128,"h":128},{"id":"voxel_pack/brick_red","name":"brick_red","category":"tile","ext":"png","rel":"2D assets/Voxel Pack/PNG/Tiles/brick_red.png","w":128,"h":128},{"id":"voxel_pack/cactus_inside","name":"cactus_inside","category":"prop","ext":"png","rel":"2D assets/Voxel Pack/PNG/Tiles/cactus_inside.png","w":128,"h":128},{"id":"voxel_pack/cactus_side","name":"cactus_side","category":"prop","ext":"png","rel":"2D assets/Voxel Pack/PNG/Tiles/cactus_side.png","w":128,"h":128},{"id":"voxel_pack/cactus_top","name":"cactus_top","category":"prop","ext":"png","rel":"2D assets/Voxel Pack/PNG/Tiles/cactus_top.png","w":128,"h":128},{"id":"voxel_pack/clouds","name":"clouds","category":"background","ext":"png","rel":"2D assets/Voxel Pack/PNG/Other/clouds.png","w":128,"h":128},{"id":"voxel_pack/cotton_blue","name":"cotton_blue","category":"prop","ext":"png","rel":"2D assets/Voxel Pack/PNG/Tiles/cotton_blue.png","w":128,"h":128},{"id":"voxel_pack/cotton_green","name":"cotton_green","category":"prop","ext":"png","rel":"2D assets/Voxel Pack/PNG/Tiles/cotton_green.png","w":128,"h":128},{"id":"voxel_pack/cotton_red","name":"cotton_red","category":"prop","ext":"png","rel":"2D assets/Voxel Pack/PNG/Tiles/cotton_red.png","w":128,"h":128},{"id":"voxel_pack/cotton_tan","name":"cotton_tan","category":"prop","ext":"png","rel":"2D assets/Voxel Pack/PNG/Tiles/cotton_tan.png","w":128,"h":128},{"id":"voxel_pack/dirt","name":"dirt","category":"tile","ext":"png","rel":"2D assets/Voxel Pack/PNG/Tiles/dirt.png","w":128,"h":128},{"id":"voxel_pack/dirt_grass","name":"dirt_grass","category":"tile","ext":"png","rel":"2D assets/Voxel Pack/PNG/Tiles/dirt_grass.png","w":128,"h":128},{"id":"voxel_pack/dirt_sand","name":"dirt_sand","category":"tile","ext":"png","rel":"2D assets/Voxel Pack/PNG/Tiles/dirt_sand.png","w":128,"h":128},{"id":"voxel_pack/dirt_snow","name":"dirt_snow","category":"tile","ext":"png","rel":"2D assets/Voxel Pack/PNG/Tiles/dirt_snow.png","w":128,"h":128},{"id":"voxel_pack/female_arm","name":"female_arm","category":"character","ext":"png","rel":"2D assets/Voxel Pack/PNG/Characters/Player female/female_arm.png","w":28,"h":66},{"id":"voxel_pack/female_body","name":"female_body","category":"character","ext":"png","rel":"2D assets/Voxel Pack/PNG/Characters/Player female/female_body.png","w":44,"h":59},{"id":"voxel_pack/female_head","name":"female_head","category":"character","ext":"png","rel":"2D assets/Voxel Pack/PNG/Characters/Player female/female_head.png","w":78,"h":72},{"id":"voxel_pack/female_leg","name":"female_leg","category":"character","ext":"png","rel":"2D assets/Voxel Pack/PNG/Characters/Player female/female_leg.png","w":28,"h":56},{"id":"voxel_pack/fence_stone","name":"fence_stone","category":"tile","ext":"png","rel":"2D assets/Voxel Pack/PNG/Tiles/fence_stone.png","w":128,"h":128},{"id":"voxel_pack/fence_wood","name":"fence_wood","category":"tile","ext":"png","rel":"2D assets/Voxel Pack/PNG/Tiles/fence_wood.png","w":128,"h":128},{"id":"voxel_pack/fish","name":"fish","category":"prop","ext":"png","rel":"2D assets/Voxel Pack/PNG/Items/fish.png","w":128,"h":128},{"id":"voxel_pack/fish_cooked","name":"fish_cooked","category":"prop","ext":"png","rel":"2D assets/Voxel Pack/PNG/Items/fish_cooked.png","w":128,"h":128},{"id":"voxel_pack/fishingPole","name":"fishingPole","category":"prop","ext":"png","rel":"2D assets/Voxel Pack/PNG/Items/fishingPole.png","w":128,"h":128},{"id":"voxel_pack/flail_bronze","name":"flail_bronze","category":"prop","ext":"png","rel":"2D assets/Voxel Pack/PNG/Items/flail_bronze.png","w":128,"h":128},{"id":"voxel_pack/flail_diamond","name":"flail_diamond","category":"item","ext":"png","rel":"2D assets/Voxel Pack/PNG/Items/flail_diamond.png","w":128,"h":128},{"id":"voxel_pack/flail_gold","name":"flail_gold","category":"item","ext":"png","rel":"2D assets/Voxel Pack/PNG/Items/flail_gold.png","w":128,"h":128},{"id":"voxel_pack/flail_iron","name":"flail_iron","category":"prop","ext":"png","rel":"2D assets/Voxel Pack/PNG/Items/flail_iron.png","w":128,"h":128},{"id":"voxel_pack/flail_silver","name":"flail_silver","category":"prop","ext":"png","rel":"2D assets/Voxel Pack/PNG/Items/flail_silver.png","w":128,"h":128},{"id":"voxel_pack/fox_body","name":"fox_body","category":"character","ext":"png","rel":"2D assets/Voxel Pack/PNG/Characters/Fox/fox_body.png","w":116,"h":54},{"id":"voxel_pack/fox_ear","name":"fox_ear","category":"character","ext":"png","rel":"2D assets/Voxel Pack/PNG/Characters/Fox/fox_ear.png","w":12,"h":20},{"id":"voxel_pack/fox_leg","name":"fox_leg","category":"character","ext":"png","rel":"2D assets/Voxel Pack/PNG/Characters/Fox/fox_leg.png","w":16,"h":23},{"id":"voxel_pack/fox_tail","name":"fox_tail","category":"character","ext":"png","rel":"2D assets/Voxel Pack/PNG/Characters/Fox/fox_tail.png","w":40,"h":20},{"id":"voxel_pack/glass","name":"glass","category":"prop","ext":"png","rel":"2D assets/Voxel Pack/PNG/Tiles/glass.png","w":128,"h":128},{"id":"voxel_pack/glass_frame","name":"glass_frame","category":"ui","ext":"png","rel":"2D assets/Voxel Pack/PNG/Tiles/glass_frame.png","w":128,"h":128},{"id":"voxel_pack/gnome_arm","name":"gnome_arm","category":"character","ext":"png","rel":"2D assets/Voxel Pack/PNG/Characters/Gnome/gnome_arm.png","w":14,"h":42},{"id":"voxel_pack/gnome_body","name":"gnome_body","category":"character","ext":"png","rel":"2D assets/Voxel Pack/PNG/Characters/Gnome/gnome_body.png","w":34,"h":36},{"id":"voxel_pack/gnome_head","name":"gnome_head","category":"character","ext":"png","rel":"2D assets/Voxel Pack/PNG/Characters/Gnome/gnome_head.png","w":44,"h":81},{"id":"voxel_pack/gnome_leg","name":"gnome_leg","category":"character","ext":"png","rel":"2D assets/Voxel Pack/PNG/Characters/Gnome/gnome_leg.png","w":24,"h":34},{"id":"voxel_pack/grass_brown","name":"grass_brown","category":"tile","ext":"png","rel":"2D assets/Voxel Pack/PNG/Tiles/grass_brown.png","w":128,"h":128},{"id":"voxel_pack/grass_tan","name":"grass_tan","category":"tile","ext":"png","rel":"2D assets/Voxel Pack/PNG/Tiles/grass_tan.png","w":128,"h":128},{"id":"voxel_pack/grass_top","name":"grass_top","category":"tile","ext":"png","rel":"2D assets/Voxel Pack/PNG/Tiles/grass_top.png","w":128,"h":128},{"id":"voxel_pack/grass1","name":"grass1","category":"tile","ext":"png","rel":"2D assets/Voxel Pack/PNG/Tiles/grass1.png","w":128,"h":128},{"id":"voxel_pack/grass2","name":"grass2","category":"tile","ext":"png","rel":"2D assets/Voxel Pack/PNG/Tiles/grass2.png","w":128,"h":128},{"id":"voxel_pack/grass3","name":"grass3","category":"tile","ext":"png","rel":"2D assets/Voxel Pack/PNG/Tiles/grass3.png","w":128,"h":128},{"id":"voxel_pack/grass4","name":"grass4","category":"tile","ext":"png","rel":"2D assets/Voxel Pack/PNG/Tiles/grass4.png","w":128,"h":128},{"id":"voxel_pack/gravel_dirt","name":"gravel_dirt","category":"tile","ext":"png","rel":"2D assets/Voxel Pack/PNG/Tiles/gravel_dirt.png","w":128,"h":128},{"id":"voxel_pack/gravel_stone","name":"gravel_stone","category":"tile","ext":"png","rel":"2D assets/Voxel Pack/PNG/Tiles/gravel_stone.png","w":128,"h":128},{"id":"voxel_pack/greysand","name":"greysand","category":"prop","ext":"png","rel":"2D assets/Voxel Pack/PNG/Tiles/greysand.png","w":128,"h":128},{"id":"voxel_pack/greystone","name":"greystone","category":"tile","ext":"png","rel":"2D assets/Voxel Pack/PNG/Tiles/greystone.png","w":128,"h":128},{"id":"voxel_pack/greystone_ruby","name":"greystone_ruby","category":"tile","ext":"png","rel":"2D assets/Voxel Pack/PNG/Tiles/greystone_ruby.png","w":128,"h":128},{"id":"voxel_pack/greystone_ruby_alt","name":"greystone_ruby_alt","category":"tile","ext":"png","rel":"2D assets/Voxel Pack/PNG/Tiles/greystone_ruby_alt.png","w":128,"h":128},{"id":"voxel_pack/greystone_sand","name":"greystone_sand","category":"tile","ext":"png","rel":"2D assets/Voxel Pack/PNG/Tiles/greystone_sand.png","w":128,"h":128},{"id":"voxel_pack/hammer_bronze","name":"hammer_bronze","category":"prop","ext":"png","rel":"2D assets/Voxel Pack/PNG/Items/hammer_bronze.png","w":128,"h":128},{"id":"voxel_pack/hammer_diamond","name":"hammer_diamond","category":"item","ext":"png","rel":"2D assets/Voxel Pack/PNG/Items/hammer_diamond.png","w":128,"h":128},{"id":"voxel_pack/hammer_gold","name":"hammer_gold","category":"item","ext":"png","rel":"2D assets/Voxel Pack/PNG/Items/hammer_gold.png","w":128,"h":128},{"id":"voxel_pack/hammer_iron","name":"hammer_iron","category":"prop","ext":"png","rel":"2D assets/Voxel Pack/PNG/Items/hammer_iron.png","w":128,"h":128},{"id":"voxel_pack/hammer_silver","name":"hammer_silver","category":"prop","ext":"png","rel":"2D assets/Voxel Pack/PNG/Items/hammer_silver.png","w":128,"h":128},{"id":"voxel_pack/hedgehog_body","name":"hedgehog_body","category":"character","ext":"png","rel":"2D assets/Voxel Pack/PNG/Characters/Hedgehog/hedgehog_body.png","w":72,"h":40},{"id":"voxel_pack/hoe_bronze","name":"hoe_bronze","category":"prop","ext":"png","rel":"2D assets/Voxel Pack/PNG/Items/hoe_bronze.png","w":128,"h":128},{"id":"voxel_pack/hoe_diamond","name":"hoe_diamond","category":"item","ext":"png","rel":"2D assets/Voxel Pack/PNG/Items/hoe_diamond.png","w":128,"h":128},{"id":"voxel_pack/hoe_gold","name":"hoe_gold","category":"item","ext":"png","rel":"2D assets/Voxel Pack/PNG/Items/hoe_gold.png","w":128,"h":128},{"id":"voxel_pack/hoe_iron","name":"hoe_iron","category":"prop","ext":"png","rel":"2D assets/Voxel Pack/PNG/Items/hoe_iron.png","w":128,"h":128},{"id":"voxel_pack/hoe_silver","name":"hoe_silver","category":"prop","ext":"png","rel":"2D assets/Voxel Pack/PNG/Items/hoe_silver.png","w":128,"h":128},{"id":"voxel_pack/ice","name":"ice","category":"prop","ext":"png","rel":"2D assets/Voxel Pack/PNG/Tiles/ice.png","w":128,"h":128},{"id":"voxel_pack/lava","name":"lava","category":"prop","ext":"png","rel":"2D assets/Voxel Pack/PNG/Tiles/lava.png","w":128,"h":128},{"id":"voxel_pack/leaves","name":"leaves","category":"prop","ext":"png","rel":"2D assets/Voxel Pack/PNG/Tiles/leaves.png","w":128,"h":128},{"id":"voxel_pack/leaves_orange","name":"leaves_orange","category":"prop","ext":"png","rel":"2D assets/Voxel Pack/PNG/Tiles/leaves_orange.png","w":128,"h":128},{"id":"voxel_pack/leaves_orange_transparent","name":"leaves_orange_transparent","category":"prop","ext":"png","rel":"2D assets/Voxel Pack/PNG/Tiles/leaves_orange_transparent.png","w":128,"h":128},{"id":"voxel_pack/leaves_transparent","name":"leaves_transparent","category":"prop","ext":"png","rel":"2D assets/Voxel Pack/PNG/Tiles/leaves_transparent.png","w":128,"h":128},{"id":"voxel_pack/male_arm","name":"male_arm","category":"character","ext":"png","rel":"2D assets/Voxel Pack/PNG/Characters/Player male/male_arm.png","w":28,"h":66},{"id":"voxel_pack/male_body","name":"male_body","category":"character","ext":"png","rel":"2D assets/Voxel Pack/PNG/Characters/Player male/male_body.png","w":44,"h":59},{"id":"voxel_pack/male_head","name":"male_head","category":"character","ext":"png","rel":"2D assets/Voxel Pack/PNG/Characters/Player male/male_head.png","w":64,"h":64},{"id":"voxel_pack/male_leg","name":"male_leg","category":"character","ext":"png","rel":"2D assets/Voxel Pack/PNG/Characters/Player male/male_leg.png","w":28,"h":56},{"id":"voxel_pack/minecart","name":"minecart","category":"prop","ext":"png","rel":"2D assets/Voxel Pack/PNG/Items/minecart.png","w":128,"h":128},{"id":"voxel_pack/moon","name":"moon","category":"background","ext":"png","rel":"2D assets/Voxel Pack/PNG/Other/moon.png","w":92,"h":92},{"id":"voxel_pack/mushroom_brown","name":"mushroom_brown","category":"item","ext":"png","rel":"2D assets/Voxel Pack/PNG/Tiles/mushroom_brown.png","w":128,"h":128},{"id":"voxel_pack/mushroom_red","name":"mushroom_red","category":"item","ext":"png","rel":"2D assets/Voxel Pack/PNG/Tiles/mushroom_red.png","w":128,"h":128},{"id":"voxel_pack/mushroom_tan","name":"mushroom_tan","category":"item","ext":"png","rel":"2D assets/Voxel Pack/PNG/Tiles/mushroom_tan.png","w":128,"h":128},{"id":"voxel_pack/ore_coal","name":"ore_coal","category":"prop","ext":"png","rel":"2D assets/Voxel Pack/PNG/Items/ore_coal.png","w":128,"h":128},{"id":"voxel_pack/ore_diamond","name":"ore_diamond","category":"item","ext":"png","rel":"2D assets/Voxel Pack/PNG/Items/ore_diamond.png","w":128,"h":128},{"id":"voxel_pack/ore_emerald","name":"ore_emerald","category":"prop","ext":"png","rel":"2D assets/Voxel Pack/PNG/Items/ore_emerald.png","w":128,"h":128},{"id":"voxel_pack/ore_gold","name":"ore_gold","category":"item","ext":"png","rel":"2D assets/Voxel Pack/PNG/Items/ore_gold.png","w":128,"h":128},{"id":"voxel_pack/ore_iron","name":"ore_iron","category":"prop","ext":"png","rel":"2D assets/Voxel Pack/PNG/Items/ore_iron.png","w":128,"h":128},{"id":"voxel_pack/ore_ironAlt","name":"ore_ironAlt","category":"prop","ext":"png","rel":"2D assets/Voxel Pack/PNG/Items/ore_ironAlt.png","w":128,"h":128},{"id":"voxel_pack/ore_ruby","name":"ore_ruby","category":"prop","ext":"png","rel":"2D assets/Voxel Pack/PNG/Items/ore_ruby.png","w":128,"h":128},{"id":"voxel_pack/ore_silver","name":"ore_silver","category":"prop","ext":"png","rel":"2D assets/Voxel Pack/PNG/Items/ore_silver.png","w":128,"h":128},{"id":"voxel_pack/oven","name":"oven","category":"prop","ext":"png","rel":"2D assets/Voxel Pack/PNG/Tiles/oven.png","w":128,"h":128},{"id":"voxel_pack/pick_bronze","name":"pick_bronze","category":"prop","ext":"png","rel":"2D assets/Voxel Pack/PNG/Items/pick_bronze.png","w":128,"h":128},{"id":"voxel_pack/pick_diamond","name":"pick_diamond","category":"item","ext":"png","rel":"2D assets/Voxel Pack/PNG/Items/pick_diamond.png","w":128,"h":128},{"id":"voxel_pack/pick_gold","name":"pick_gold","category":"item","ext":"png","rel":"2D assets/Voxel Pack/PNG/Items/pick_gold.png","w":128,"h":128},{"id":"voxel_pack/pick_iron","name":"pick_iron","category":"prop","ext":"png","rel":"2D assets/Voxel Pack/PNG/Items/pick_iron.png","w":128,"h":128},{"id":"voxel_pack/pick_silver","name":"pick_silver","category":"prop","ext":"png","rel":"2D assets/Voxel Pack/PNG/Items/pick_silver.png","w":128,"h":128},{"id":"voxel_pack/redsand","name":"redsand","category":"prop","ext":"png","rel":"2D assets/Voxel Pack/PNG/Tiles/redsand.png","w":128,"h":128},{"id":"voxel_pack/redstone","name":"redstone","category":"tile","ext":"png","rel":"2D assets/Voxel Pack/PNG/Tiles/redstone.png","w":128,"h":128},{"id":"voxel_pack/redstone_emerald","name":"redstone_emerald","category":"tile","ext":"png","rel":"2D assets/Voxel Pack/PNG/Tiles/redstone_emerald.png","w":128,"h":128},{"id":"voxel_pack/redstone_emerald_alt","name":"redstone_emerald_alt","category":"tile","ext":"png","rel":"2D assets/Voxel Pack/PNG/Tiles/redstone_emerald_alt.png","w":128,"h":128},{"id":"voxel_pack/redstone_sand","name":"redstone_sand","category":"tile","ext":"png","rel":"2D assets/Voxel Pack/PNG/Tiles/redstone_sand.png","w":128,"h":128},{"id":"voxel_pack/rock","name":"rock","category":"prop","ext":"png","rel":"2D assets/Voxel Pack/PNG/Tiles/rock.png","w":128,"h":128},{"id":"voxel_pack/rock_moss","name":"rock_moss","category":"prop","ext":"png","rel":"2D assets/Voxel Pack/PNG/Tiles/rock_moss.png","w":128,"h":128},{"id":"voxel_pack/sand","name":"sand","category":"tile","ext":"png","rel":"2D assets/Voxel Pack/PNG/Tiles/sand.png","w":128,"h":128},{"id":"voxel_pack/seed","name":"seed","category":"prop","ext":"png","rel":"2D assets/Voxel Pack/PNG/Items/seed.png","w":128,"h":128},{"id":"voxel_pack/shovel_bronze","name":"shovel_bronze","category":"prop","ext":"png","rel":"2D assets/Voxel Pack/PNG/Items/shovel_bronze.png","w":128,"h":128},{"id":"voxel_pack/shovel_diamond","name":"shovel_diamond","category":"item","ext":"png","rel":"2D assets/Voxel Pack/PNG/Items/shovel_diamond.png","w":128,"h":128},{"id":"voxel_pack/shovel_gold","name":"shovel_gold","category":"item","ext":"png","rel":"2D assets/Voxel Pack/PNG/Items/shovel_gold.png","w":128,"h":128},{"id":"voxel_pack/shovel_iron","name":"shovel_iron","category":"prop","ext":"png","rel":"2D assets/Voxel Pack/PNG/Items/shovel_iron.png","w":128,"h":128},{"id":"voxel_pack/shovel_silver","name":"shovel_silver","category":"prop","ext":"png","rel":"2D assets/Voxel Pack/PNG/Items/shovel_silver.png","w":128,"h":128},{"id":"voxel_pack/skeleton_arm","name":"skeleton_arm","category":"enemy","ext":"png","rel":"2D assets/Voxel Pack/PNG/Characters/Skeleton/skeleton_arm.png","w":20,"h":66},{"id":"voxel_pack/skeleton_body","name":"skeleton_body","category":"enemy","ext":"png","rel":"2D assets/Voxel Pack/PNG/Characters/Skeleton/skeleton_body.png","w":44,"h":60},{"id":"voxel_pack/skeleton_head","name":"skeleton_head","category":"enemy","ext":"png","rel":"2D assets/Voxel Pack/PNG/Characters/Skeleton/skeleton_head.png","w":64,"h":64},{"id":"voxel_pack/skeleton_leg","name":"skeleton_leg","category":"enemy","ext":"png","rel":"2D assets/Voxel Pack/PNG/Characters/Skeleton/skeleton_leg.png","w":24,"h":56},{"id":"voxel_pack/skybox_bottom","name":"skybox_bottom","category":"prop","ext":"png","rel":"2D assets/Voxel Pack/PNG/Other/skybox_bottom.png","w":512,"h":513},{"id":"voxel_pack/skybox_side","name":"skybox_side","category":"prop","ext":"png","rel":"2D assets/Voxel Pack/PNG/Other/skybox_side.png","w":512,"h":513},{"id":"voxel_pack/skybox_sideClouds","name":"skybox_sideClouds","category":"background","ext":"png","rel":"2D assets/Voxel Pack/PNG/Other/skybox_sideClouds.png","w":513,"h":513},{"id":"voxel_pack/skybox_sideHills","name":"skybox_sideHills","category":"prop","ext":"png","rel":"2D assets/Voxel Pack/PNG/Other/skybox_sideHills.png","w":512,"h":513},{"id":"voxel_pack/skybox_top","name":"skybox_top","category":"prop","ext":"png","rel":"2D assets/Voxel Pack/PNG/Other/skybox_top.png","w":512,"h":512},{"id":"voxel_pack/snow","name":"snow","category":"tile","ext":"png","rel":"2D assets/Voxel Pack/PNG/Tiles/snow.png","w":128,"h":128},{"id":"voxel_pack/square_blue","name":"square_blue","category":"effect","ext":"png","rel":"2D assets/Voxel Pack/PNG/Particles/square_blue.png","w":16,"h":16},{"id":"voxel_pack/square_orange","name":"square_orange","category":"effect","ext":"png","rel":"2D assets/Voxel Pack/PNG/Particles/square_orange.png","w":16,"h":16},{"id":"voxel_pack/square_red","name":"square_red","category":"effect","ext":"png","rel":"2D assets/Voxel Pack/PNG/Particles/square_red.png","w":16,"h":16},{"id":"voxel_pack/square_white","name":"square_white","category":"effect","ext":"png","rel":"2D assets/Voxel Pack/PNG/Particles/square_white.png","w":16,"h":16},{"id":"voxel_pack/stew","name":"stew","category":"prop","ext":"png","rel":"2D assets/Voxel Pack/PNG/Items/stew.png","w":128,"h":128},{"id":"voxel_pack/stone","name":"stone","category":"tile","ext":"png","rel":"2D assets/Voxel Pack/PNG/Tiles/stone.png","w":128,"h":128},{"id":"voxel_pack/stone_browniron","name":"stone_browniron","category":"tile","ext":"png","rel":"2D assets/Voxel Pack/PNG/Tiles/stone_browniron.png","w":128,"h":128},{"id":"voxel_pack/stone_browniron_alt","name":"stone_browniron_alt","category":"tile","ext":"png","rel":"2D assets/Voxel Pack/PNG/Tiles/stone_browniron_alt.png","w":128,"h":128},{"id":"voxel_pack/stone_coal","name":"stone_coal","category":"tile","ext":"png","rel":"2D assets/Voxel Pack/PNG/Tiles/stone_coal.png","w":128,"h":128},{"id":"voxel_pack/stone_coal_alt","name":"stone_coal_alt","category":"tile","ext":"png","rel":"2D assets/Voxel Pack/PNG/Tiles/stone_coal_alt.png","w":128,"h":128},{"id":"voxel_pack/stone_diamond","name":"stone_diamond","category":"item","ext":"png","rel":"2D assets/Voxel Pack/PNG/Tiles/stone_diamond.png","w":128,"h":128},{"id":"voxel_pack/stone_diamond_alt","name":"stone_diamond_alt","category":"item","ext":"png","rel":"2D assets/Voxel Pack/PNG/Tiles/stone_diamond_alt.png","w":128,"h":128},{"id":"voxel_pack/stone_dirt","name":"stone_dirt","category":"tile","ext":"png","rel":"2D assets/Voxel Pack/PNG/Tiles/stone_dirt.png","w":128,"h":128},{"id":"voxel_pack/stone_gold","name":"stone_gold","category":"item","ext":"png","rel":"2D assets/Voxel Pack/PNG/Tiles/stone_gold.png","w":128,"h":128},{"id":"voxel_pack/stone_gold_alt","name":"stone_gold_alt","category":"item","ext":"png","rel":"2D assets/Voxel Pack/PNG/Tiles/stone_gold_alt.png","w":128,"h":128},{"id":"voxel_pack/stone_grass","name":"stone_grass","category":"tile","ext":"png","rel":"2D assets/Voxel Pack/PNG/Tiles/stone_grass.png","w":128,"h":128},{"id":"voxel_pack/stone_iron","name":"stone_iron","category":"tile","ext":"png","rel":"2D assets/Voxel Pack/PNG/Tiles/stone_iron.png","w":128,"h":128},{"id":"voxel_pack/stone_iron_alt","name":"stone_iron_alt","category":"tile","ext":"png","rel":"2D assets/Voxel Pack/PNG/Tiles/stone_iron_alt.png","w":128,"h":128},{"id":"voxel_pack/stone_sand","name":"stone_sand","category":"tile","ext":"png","rel":"2D assets/Voxel Pack/PNG/Tiles/stone_sand.png","w":128,"h":128},{"id":"voxel_pack/stone_silver","name":"stone_silver","category":"tile","ext":"png","rel":"2D assets/Voxel Pack/PNG/Tiles/stone_silver.png","w":128,"h":128},{"id":"voxel_pack/stone_silver_alt","name":"stone_silver_alt","category":"tile","ext":"png","rel":"2D assets/Voxel Pack/PNG/Tiles/stone_silver_alt.png","w":128,"h":128},{"id":"voxel_pack/stone_snow","name":"stone_snow","category":"tile","ext":"png","rel":"2D assets/Voxel Pack/PNG/Tiles/stone_snow.png","w":128,"h":128},{"id":"voxel_pack/sun","name":"sun","category":"background","ext":"png","rel":"2D assets/Voxel Pack/PNG/Other/sun.png","w":92,"h":92},{"id":"voxel_pack/swirl_blue","name":"swirl_blue","category":"effect","ext":"png","rel":"2D assets/Voxel Pack/PNG/Particles/swirl_blue.png","w":36,"h":34},{"id":"voxel_pack/swirl_orange","name":"swirl_orange","category":"effect","ext":"png","rel":"2D assets/Voxel Pack/PNG/Particles/swirl_orange.png","w":36,"h":34},{"id":"voxel_pack/swirl_red","name":"swirl_red","category":"effect","ext":"png","rel":"2D assets/Voxel Pack/PNG/Particles/swirl_red.png","w":36,"h":34},{"id":"voxel_pack/swirl_white","name":"swirl_white","category":"effect","ext":"png","rel":"2D assets/Voxel Pack/PNG/Particles/swirl_white.png","w":36,"h":34},{"id":"voxel_pack/sword_bronze","name":"sword_bronze","category":"prop","ext":"png","rel":"2D assets/Voxel Pack/PNG/Items/sword_bronze.png","w":128,"h":128},{"id":"voxel_pack/sword_diamond","name":"sword_diamond","category":"item","ext":"png","rel":"2D assets/Voxel Pack/PNG/Items/sword_diamond.png","w":128,"h":128},{"id":"voxel_pack/sword_gold","name":"sword_gold","category":"item","ext":"png","rel":"2D assets/Voxel Pack/PNG/Items/sword_gold.png","w":128,"h":128},{"id":"voxel_pack/sword_iron","name":"sword_iron","category":"prop","ext":"png","rel":"2D assets/Voxel Pack/PNG/Items/sword_iron.png","w":128,"h":128},{"id":"voxel_pack/sword_silver","name":"sword_silver","category":"prop","ext":"png","rel":"2D assets/Voxel Pack/PNG/Items/sword_silver.png","w":128,"h":128},{"id":"voxel_pack/table","name":"table","category":"prop","ext":"png","rel":"2D assets/Voxel Pack/PNG/Tiles/table.png","w":128,"h":128},{"id":"voxel_pack/track_corner","name":"track_corner","category":"prop","ext":"png","rel":"2D assets/Voxel Pack/PNG/Tiles/track_corner.png","w":128,"h":128},{"id":"voxel_pack/track_corner_alt","name":"track_corner_alt","category":"prop","ext":"png","rel":"2D assets/Voxel Pack/PNG/Tiles/track_corner_alt.png","w":128,"h":128},{"id":"voxel_pack/track_straight","name":"track_straight","category":"prop","ext":"png","rel":"2D assets/Voxel Pack/PNG/Tiles/track_straight.png","w":128,"h":128},{"id":"voxel_pack/track_straight_alt","name":"track_straight_alt","category":"prop","ext":"png","rel":"2D assets/Voxel Pack/PNG/Tiles/track_straight_alt.png","w":128,"h":128},{"id":"voxel_pack/trunk_bottom","name":"trunk_bottom","category":"prop","ext":"png","rel":"2D assets/Voxel Pack/PNG/Tiles/trunk_bottom.png","w":128,"h":128},{"id":"voxel_pack/trunk_mid","name":"trunk_mid","category":"prop","ext":"png","rel":"2D assets/Voxel Pack/PNG/Tiles/trunk_mid.png","w":128,"h":128},{"id":"voxel_pack/trunk_side","name":"trunk_side","category":"prop","ext":"png","rel":"2D assets/Voxel Pack/PNG/Tiles/trunk_side.png","w":128,"h":128},{"id":"voxel_pack/trunk_top","name":"trunk_top","category":"prop","ext":"png","rel":"2D assets/Voxel Pack/PNG/Tiles/trunk_top.png","w":128,"h":128},{"id":"voxel_pack/trunk_white_side","name":"trunk_white_side","category":"prop","ext":"png","rel":"2D assets/Voxel Pack/PNG/Tiles/trunk_white_side.png","w":128,"h":128},{"id":"voxel_pack/trunk_white_top","name":"trunk_white_top","category":"prop","ext":"png","rel":"2D assets/Voxel Pack/PNG/Tiles/trunk_white_top.png","w":128,"h":128},{"id":"voxel_pack/vector_characters","name":"vector_characters","category":"character","ext":"svg","rel":"2D assets/Voxel Pack/Vector/vector_characters.svg"},{"id":"voxel_pack/vector_other","name":"vector_other","category":"prop","ext":"svg","rel":"2D assets/Voxel Pack/Vector/vector_other.svg"},{"id":"voxel_pack/vector_tiles_items","name":"vector_tiles_items","category":"prop","ext":"svg","rel":"2D assets/Voxel Pack/Vector/vector_tiles_items.svg"},{"id":"voxel_pack/water","name":"water","category":"background","ext":"png","rel":"2D assets/Voxel Pack/PNG/Tiles/water.png","w":128,"h":128},{"id":"voxel_pack/wheat","name":"wheat","category":"prop","ext":"png","rel":"2D assets/Voxel Pack/PNG/Items/wheat.png","w":128,"h":128},{"id":"voxel_pack/wheat_stage1","name":"wheat_stage1","category":"prop","ext":"png","rel":"2D assets/Voxel Pack/PNG/Tiles/wheat_stage1.png","w":128,"h":128},{"id":"voxel_pack/wheat_stage2","name":"wheat_stage2","category":"prop","ext":"png","rel":"2D assets/Voxel Pack/PNG/Tiles/wheat_stage2.png","w":128,"h":128},{"id":"voxel_pack/wheat_stage3","name":"wheat_stage3","category":"prop","ext":"png","rel":"2D assets/Voxel Pack/PNG/Tiles/wheat_stage3.png","w":128,"h":128},{"id":"voxel_pack/wheat_stage4","name":"wheat_stage4","category":"prop","ext":"png","rel":"2D assets/Voxel Pack/PNG/Tiles/wheat_stage4.png","w":128,"h":128},{"id":"voxel_pack/wood","name":"wood","category":"prop","ext":"png","rel":"2D assets/Voxel Pack/PNG/Tiles/wood.png","w":128,"h":128},{"id":"voxel_pack/wood_red","name":"wood_red","category":"prop","ext":"png","rel":"2D assets/Voxel Pack/PNG/Tiles/wood_red.png","w":128,"h":128},{"id":"voxel_pack/zombie_arm","name":"zombie_arm","category":"enemy","ext":"png","rel":"2D assets/Voxel Pack/PNG/Characters/Zombie/zombie_arm.png","w":28,"h":66},{"id":"voxel_pack/zombie_body","name":"zombie_body","category":"enemy","ext":"png","rel":"2D assets/Voxel Pack/PNG/Characters/Zombie/zombie_body.png","w":44,"h":59},{"id":"voxel_pack/zombie_head","name":"zombie_head","category":"enemy","ext":"png","rel":"2D assets/Voxel Pack/PNG/Characters/Zombie/zombie_head.png","w":64,"h":64},{"id":"voxel_pack/zombie_leg","name":"zombie_leg","category":"enemy","ext":"png","rel":"2D assets/Voxel Pack/PNG/Characters/Zombie/zombie_leg.png","w":28,"h":56}]}